<?xml version="1.0"?>
<trafficlist>
    <aircraft>
        <model>Aircraft/A332/A332-JetAirways.xml</model>
        <livery>JAI</livery>
        <airline>JAI</airline>
        <home-port>VABB</home-port>
        <required-aircraft>A332JAI</required-aircraft>
        <actype>A330-202</actype>
        <offset>0</offset>
        <radius>30</radius>
        <flighttype>gate</flighttype>
        <performance-class>jet_transport</performance-class>
        <registration>VT-JWF</registration>
        <heavy>false</heavy>
    </aircraft>
    <aircraft>
        <model>Aircraft/A332/A332-JetAirways.xml</model>
        <livery>JAI</livery>
        <airline>JAI</airline>
        <home-port>VABB</home-port>
        <required-aircraft>A332JAI</required-aircraft>
        <actype>A330-202</actype>
        <offset>0</offset>
        <radius>30</radius>
        <flighttype>gate</flighttype>
        <performance-class>jet_transport</performance-class>
        <registration>VT-JWG</registration>
        <heavy>false</heavy>
    </aircraft>
    <aircraft>
        <model>Aircraft/A332/A332-JetAirways.xml</model>
        <livery>JAI</livery>
        <airline>JAI</airline>
        <home-port>VABB</home-port>
        <required-aircraft>A332JAI</required-aircraft>
        <actype>A330-202</actype>
        <offset>0</offset>
        <radius>30</radius>
        <flighttype>gate</flighttype>
        <performance-class>jet_transport</performance-class>
        <registration>VT-JWH</registration>
        <heavy>false</heavy>
    </aircraft>
    <aircraft>
        <model>Aircraft/A332/A332-JetAirways.xml</model>
        <livery>JAI</livery>
        <airline>JAI</airline>
        <home-port>VABB</home-port>
        <required-aircraft>A332JAI</required-aircraft>
        <actype>A330-202</actype>
        <offset>0</offset>
        <radius>30</radius>
        <flighttype>gate</flighttype>
        <performance-class>jet_transport</performance-class>
        <registration>VT-JWJ</registration>
        <heavy>false</heavy>
    </aircraft>
    <aircraft>
        <model>Aircraft/A332/A332-JetAirways.xml</model>
        <livery>JAI</livery>
        <airline>JAI</airline>
        <home-port>VABB</home-port>
        <required-aircraft>A332JAI</required-aircraft>
        <actype>A330-202</actype>
        <offset>0</offset>
        <radius>30</radius>
        <flighttype>gate</flighttype>
        <performance-class>jet_transport</performance-class>
        <registration>VT-JWK</registration>
        <heavy>false</heavy>
    </aircraft>
    <aircraft>
        <model>Aircraft/A332/A332-JetAirways.xml</model>
        <livery>JAI</livery>
        <airline>JAI</airline>
        <home-port>VABB</home-port>
        <required-aircraft>A332JAI</required-aircraft>
        <actype>A330-202</actype>
        <offset>0</offset>
        <radius>30</radius>
        <flighttype>gate</flighttype>
        <performance-class>jet_transport</performance-class>
        <registration>VT-JWL</registration>
        <heavy>false</heavy>
    </aircraft>
    <aircraft>
        <model>Aircraft/A332/A332-JetAirways.xml</model>
        <livery>JAI</livery>
        <airline>JAI</airline>
        <home-port>VABB</home-port>
        <required-aircraft>A332JAI</required-aircraft>
        <actype>A330-202</actype>
        <offset>0</offset>
        <radius>30</radius>
        <flighttype>gate</flighttype>
        <performance-class>jet_transport</performance-class>
        <registration>VT-JWM</registration>
        <heavy>false</heavy>
    </aircraft>
    <aircraft>
        <model>Aircraft/A332/A332-JetAirways.xml</model>
        <livery>JAI</livery>
        <airline>JAI</airline>
        <home-port>VABB</home-port>
        <required-aircraft>A332JAI</required-aircraft>
        <actype>A330-202</actype>
        <offset>0</offset>
        <radius>30</radius>
        <flighttype>gate</flighttype>
        <performance-class>jet_transport</performance-class>
        <registration>VT-JWN</registration>
        <heavy>false</heavy>
    </aircraft>
    <aircraft>
        <model>Aircraft/A332/A332-JetAirways.xml</model>
        <livery>JAI</livery>
        <airline>JAI</airline>
        <home-port>VABB</home-port>
        <required-aircraft>A332JAI</required-aircraft>
        <actype>A330-202</actype>
        <offset>0</offset>
        <radius>30</radius>
        <flighttype>gate</flighttype>
        <performance-class>jet_transport</performance-class>
        <registration>VT-JWP</registration>
        <heavy>false</heavy>
    </aircraft>
    <aircraft>
        <model>Aircraft/A332/A332-JetAirways.xml</model>
        <livery>JAI</livery>
        <airline>JAI</airline>
        <home-port>VABB</home-port>
        <required-aircraft>A332JAI</required-aircraft>
        <actype>A330-202</actype>
        <offset>0</offset>
        <radius>30</radius>
        <flighttype>gate</flighttype>
        <performance-class>jet_transport</performance-class>
        <registration>VT-JWQ</registration>
        <heavy>false</heavy>
    </aircraft>    
       <flight>
            <callsign>JET-AIRWAYS-535</callsign>
            <required-aircraft>A332JAI</required-aircraft>
            <fltrules>IFR</fltrules>
            <departure>
                <port>OMDB</port>
                <time>11:20:00</time>
            </departure>
            <cruise-alt>360</cruise-alt>
            <arrival>
                <port>VABB</port>
                <time>14:25:00</time>
            </arrival>
            <repeat>24Hr</repeat>
        </flight>  
        <flight>
            <callsign>JET-AIRWAYS-537</callsign>
            <required-aircraft>A332JAI</required-aircraft>
            <fltrules>IFR</fltrules>
            <departure>
                <port>OMDB</port>
                <time>14:45:00</time>
            </departure>
            <cruise-alt>360</cruise-alt>
            <arrival>
                <port>VABB</port>
                <time>17:50:00</time>
            </arrival>
            <repeat>24Hr</repeat>
        </flight>
        <flight>
            <callsign>JET-AIRWAYS-541</callsign>
            <required-aircraft>A332JAI</required-aircraft>
            <fltrules>IFR</fltrules>
            <departure>
                <port>OMDB</port>
                <time>08:00:00</time>
            </departure>
            <cruise-alt>360</cruise-alt>
            <arrival>
                <port>VABB</port>
                <time>11:05:00</time>
            </arrival>
            <repeat>24Hr</repeat>
        </flight>
        <flight>
            <callsign>JET-AIRWAYS-543</callsign>
            <required-aircraft>A332JAI</required-aircraft>
            <fltrules>IFR</fltrules>
            <departure>
                <port>OMDB</port>
                <time>17:40:00</time>
            </departure>
            <cruise-alt>360</cruise-alt>
            <arrival>
                <port>VABB</port>
                <time>20:45:00</time>
            </arrival>
            <repeat>24Hr</repeat>
        </flight>
        <flight>
            <callsign>JET-AIRWAYS-536</callsign>
            <required-aircraft>A332JAI</required-aircraft>
            <fltrules>IFR</fltrules>
            <departure>
                <port>VABB</port>
                <time>06:55:00</time>
            </departure>
            <cruise-alt>360</cruise-alt>
            <arrival>
                <port>OMDB</port>
                <time>09:55:00</time>
            </arrival>
            <repeat>24Hr</repeat>
        </flight> 
        <flight>
            <callsign>JET-AIRWAYS-538</callsign>
            <required-aircraft>A332JAI</required-aircraft>
            <fltrules>IFR</fltrules>
            <departure>
                <port>VABB</port>
                <time>10:05:00</time>
            </departure>
            <cruise-alt>360</cruise-alt>
            <arrival>
                <port>OMDB</port>
                <time>13:10:00</time>
            </arrival>
            <repeat>24Hr</repeat>
        </flight>
        <flight>
            <callsign>JET-AIRWAYS-542</callsign>
            <required-aircraft>A332JAI</required-aircraft>
            <fltrules>IFR</fltrules>
            <departure>
                <port>VABB</port>
                <time>03:55:00</time>
            </departure>
            <cruise-alt>360</cruise-alt>
            <arrival>
                <port>OMDB</port>
                <time>07:00:00</time>
            </arrival>
            <repeat>24Hr</repeat>
        </flight>
        <flight>
            <callsign>JET-AIRWAYS-544</callsign>
            <required-aircraft>A332JAI</required-aircraft>
            <fltrules>IFR</fltrules>
            <departure>
                <port>VABB</port>
                <time>13:30:00</time>
            </departure>
            <cruise-alt>360</cruise-alt>
            <arrival>
                <port>OMDB</port>
                <time>16:35:00</time>
            </arrival>
            <repeat>24Hr</repeat>
        </flight> 
        <flight>
            <callsign>JET-AIRWAYS-545</callsign>
            <required-aircraft>A332JAI</required-aircraft>
            <fltrules>IFR</fltrules>
            <departure>
                <port>OMDB</port>
                <time>10:45:00</time>
            </departure>
            <cruise-alt>360</cruise-alt>
            <arrival>
                <port>VIDP</port>
                <time>14:05:00</time>
            </arrival>
            <repeat>24Hr</repeat>
        </flight>
        <flight>
            <callsign>JET-AIRWAYS-547</callsign>
            <required-aircraft>A332JAI</required-aircraft>
            <fltrules>IFR</fltrules>
            <departure>
                <port>OMDB</port>
                <time>18:55:00</time>
            </departure>
            <cruise-alt>360</cruise-alt>
            <arrival>
                <port>VIDP</port>
                <time>22:15:00</time>
            </arrival>
            <repeat>24Hr</repeat>
        </flight>
        <flight>
            <callsign>JET-AIRWAYS-546</callsign>
            <required-aircraft>A332JAI</required-aircraft>
            <fltrules>IFR</fltrules>
            <departure>
                <port>VIDP</port>
                <time>06:05:00</time>
            </departure>
            <cruise-alt>360</cruise-alt>
            <arrival>
                <port>OMDB</port>
                <time>09:45:00</time>
            </arrival>
            <repeat>24Hr</repeat>
        </flight>
        <flight>
            <callsign>JET-AIRWAYS-548</callsign>
            <required-aircraft>A332JAI</required-aircraft>
            <fltrules>IFR</fltrules>
            <departure>
                <port>VIDP</port>
                <time>14:00:00</time>
            </departure>
            <cruise-alt>360</cruise-alt>
            <arrival>
                <port>OMDB</port>
                <time>17:35:00</time>
            </arrival>
            <repeat>24Hr</repeat>
        </flight> 
        <flight>
            <callsign>JET-AIRWAYS-531</callsign>
            <required-aircraft>A332JAI</required-aircraft>
            <fltrules>IFR</fltrules>
            <departure>
                <port>OMDB</port>
                <time>22:20:00</time>
            </departure>
            <cruise-alt>360</cruise-alt>
            <arrival>
                <port>VOML</port>
                <time>02:05:00</time>
            </arrival>
            <repeat>24Hr</repeat>
        </flight>  
        <flight>
            <callsign>JET-AIRWAYS-532</callsign>
            <required-aircraft>A332JAI</required-aircraft>
            <fltrules>IFR</fltrules>
            <departure>
                <port>VOML</port>
                <time>17:35:00</time>
            </departure>
            <cruise-alt>360</cruise-alt>
            <arrival>
                <port>OMDB</port>
                <time>21:20:00</time>
            </arrival>
            <repeat>24Hr</repeat>
        </flight> 
         <flight>
            <callsign>JET-AIRWAYS-18</callsign>
            <required-aircraft>A332JAI</required-aircraft>
            <fltrules>IFR</fltrules>
            <departure>
                <port>VIDP</port>
                <time>03:15:00</time>
            </departure>
            <cruise-alt>360</cruise-alt>
            <arrival>
                <port>WSSS</port>
                <time>09:05:00</time>
            </arrival>
            <repeat>24Hr</repeat>
        </flight>  
        <flight>
            <callsign>JET-AIRWAYS-20</callsign>
            <required-aircraft>A332JAI</required-aircraft>
            <fltrules>IFR</fltrules>
            <departure>
                <port>VIDP</port>
                <time>16:50:00</time>
            </departure>
            <cruise-alt>360</cruise-alt>
            <arrival>
                <port>WSSS</port>
                <time>22:40:00</time>
            </arrival>
            <repeat>24Hr</repeat>
        </flight>
        <flight>
            <callsign>JET-AIRWAYS-17</callsign>
            <required-aircraft>A332JAI</required-aircraft>
            <fltrules>IFR</fltrules>
            <departure>
                <port>WSSS</port>
                <time>11:35:00</time>
            </departure>
            <cruise-alt>360</cruise-alt>
            <arrival>
                <port>VIDP</port>
                <time>17:20:00</time>
            </arrival>
            <repeat>24Hr</repeat>
        </flight> 
        <flight>
            <callsign>JET-AIRWAYS-19</callsign>
            <required-aircraft>A332JAI</required-aircraft>
            <fltrules>IFR</fltrules>
            <departure>
                <port>WSSS</port>
                <time>01:15:00</time>
            </departure>
            <cruise-alt>360</cruise-alt>
            <arrival>
                <port>VIDP</port>
                <time>07:05:00</time>
            </arrival>
            <repeat>24Hr</repeat>
        </flight>
        <flight>
            <callsign>JET-AIRWAYS-12</callsign>
            <required-aircraft>A332JAI</required-aircraft>
            <fltrules>IFR</fltrules>
            <departure>
                <port>VABB</port>
                <time>18:00:00</time>
            </departure>
            <cruise-alt>360</cruise-alt>
            <arrival>
                <port>WSSS</port>
                <time>23:25:00</time>
            </arrival>
            <repeat>24Hr</repeat>
        </flight> 
        <flight>
            <callsign>JET-AIRWAYS-11</callsign>
            <required-aircraft>A332JAI</required-aircraft>
            <fltrules>IFR</fltrules>
            <departure>
                <port>WSSS</port>
                <time>11:05:00</time>
            </departure>
            <cruise-alt>360</cruise-alt>
            <arrival>
                <port>VABB</port>
                <time>16:30:00</time>
            </arrival>
            <repeat>24Hr</repeat>
        </flight>
        <flight>
            <callsign>JET-AIRWAYS-16</callsign>
            <required-aircraft>A332JAI</required-aircraft>
            <fltrules>IFR</fltrules>
            <departure>
                <port>VOMM</port>
                <time>19:45:00</time>
            </departure>
            <cruise-alt>360</cruise-alt>
            <arrival>
                <port>WSSS</port>
                <time>00:05:00</time>
            </arrival>
            <repeat>24Hr</repeat>
        </flight> 
        <flight>
            <callsign>JET-AIRWAYS-15</callsign>
            <required-aircraft>A332JAI</required-aircraft>
            <fltrules>IFR</fltrules>
            <departure>
                <port>WSSS</port>
                <time>01:15:00</time>
            </departure>
            <cruise-alt>360</cruise-alt>
            <arrival>
                <port>VOMM</port>
                <time>05:30:00</time>
            </arrival>
            <repeat>24Hr</repeat>
        </flight>         
</trafficlist>
