<?xml version="1.0"?>
<trafficlist>
    <aircraft>
        <model>Aircraft/737/737-PegasusAirlines.xml</model>
        <livery>PGT</livery>
        <airline>PGT</airline>
        <home-port>LTAY</home-port>
        <required-aircraft>737PGT</required-aircraft>
        <actype>737-4Y0</actype>
        <offset>10</offset>
        <radius>14</radius>
        <flighttype>gate</flighttype>
        <performance-class>jet_transport</performance-class>
        <registration>TC-APR</registration>
        <heavy>false</heavy>
    </aircraft>
    <aircraft>
        <model>Aircraft/737/737-PegasusAirlines.xml</model>
        <livery>PGT</livery>
        <airline>PGT</airline>
        <home-port>LTAY</home-port>
        <required-aircraft>737PGT</required-aircraft>
        <actype>737-48E</actype>
        <offset>10</offset>
        <radius>14</radius>
        <flighttype>gate</flighttype>
        <performance-class>jet_transport</performance-class>
        <registration>TC-SGE</registration>
        <heavy>false</heavy>
    </aircraft>
    <aircraft>
        <model>Aircraft/737/737-PegasusAirlines.xml</model>
        <livery>PGT</livery>
        <airline>PGT</airline>
        <home-port>LTAY</home-port>
        <required-aircraft>737PGT</required-aircraft>
        <actype>737-5Q8</actype>
        <offset>10</offset>
        <radius>14</radius>
        <flighttype>gate</flighttype>
        <performance-class>jet_transport</performance-class>
        <registration>TC-AAD</registration>
        <heavy>false</heavy>
    </aircraft>
    <aircraft>
        <model>Aircraft/737/737-PegasusAirlines.xml</model>
        <livery>PGT</livery>
        <airline>PGT</airline>
        <home-port>LTAY</home-port>
        <required-aircraft>737PGT</required-aircraft>
        <actype>737-42R</actype>
        <offset>10</offset>
        <radius>14</radius>
        <flighttype>gate</flighttype>
        <performance-class>jet_transport</performance-class>
        <registration>TC-APD</registration>
        <heavy>false</heavy>
    </aircraft>
    <aircraft>
        <model>Aircraft/737/737-PegasusAirlines.xml</model>
        <livery>PGT</livery>
        <airline>PGT</airline>
        <home-port>LTAY</home-port>
        <required-aircraft>737PGT</required-aircraft>
        <actype>737-58E</actype>
        <offset>10</offset>
        <radius>14</radius>
        <flighttype>gate</flighttype>
        <performance-class>jet_transport</performance-class>
        <registration>TC-AAF</registration>
        <heavy>false</heavy>
    </aircraft>
    <aircraft>
        <model>Aircraft/737/737-PegasusAirlines.xml</model>
        <livery>PGT</livery>
        <airline>PGT</airline>
        <home-port>LTAY</home-port>
        <required-aircraft>737PGT</required-aircraft>
        <actype>737-5L9</actype>
        <offset>10</offset>
        <radius>14</radius>
        <flighttype>gate</flighttype>
        <performance-class>jet_transport</performance-class>
        <registration>TC-AAG</registration>
        <heavy>false</heavy>
    </aircraft>
    <aircraft>
        <model>Aircraft/737/737-PegasusAirlines.xml</model>
        <livery>PGT</livery>
        <airline>PGT</airline>
        <home-port>LTFJ</home-port>
        <required-aircraft>737LTFJPGT</required-aircraft>
        <actype>737-8S3</actype>
        <offset>10</offset>
        <radius>14</radius>
        <flighttype>gate</flighttype>
        <performance-class>jet_transport</performance-class>
        <registration>TC-APH</registration>
        <heavy>false</heavy>
    </aircraft>
    <aircraft>
        <model>Aircraft/737/737-PegasusAirlines.xml</model>
        <livery>PGT</livery>
        <airline>PGT</airline>
        <home-port>LTFJ</home-port>
        <required-aircraft>737LTFJPGT</required-aircraft>
        <actype>737-86N</actype>
        <offset>10</offset>
        <radius>14</radius>
        <flighttype>gate</flighttype>
        <performance-class>jet_transport</performance-class>
        <registration>TC-SPJ</registration>
        <heavy>false</heavy>
    </aircraft>
    <aircraft>
        <model>Aircraft/737/737-PegasusAirlines.xml</model>
        <livery>PGT</livery>
        <airline>PGT</airline>
        <home-port>LTFJ</home-port>
        <required-aircraft>737LTFJPGT</required-aircraft>
        <actype>737-86N</actype>
        <offset>10</offset>
        <radius>14</radius>
        <flighttype>gate</flighttype>
        <performance-class>jet_transport</performance-class>
        <registration>TC-AAP</registration>
        <heavy>false</heavy>
    </aircraft>
    <aircraft>
        <model>Aircraft/737/737-PegasusAirlines.xml</model>
        <livery>PGT</livery>
        <airline>PGT</airline>
        <home-port>LTFJ</home-port>
        <required-aircraft>737LTFJPGT</required-aircraft>
        <actype>737-4FH</actype>
        <offset>10</offset>
        <radius>14</radius>
        <flighttype>gate</flighttype>
        <performance-class>jet_transport</performance-class>
        <registration>TC-AAK</registration>
        <heavy>false</heavy>
    </aircraft>
    <aircraft>
        <model>Aircraft/737/737-PegasusAirlines.xml</model>
        <livery>PGT</livery>
        <airline>PGT</airline>
        <home-port>LTFJ</home-port>
        <required-aircraft>737LTFJPGT</required-aircraft>
        <actype>737-82R</actype>
        <offset>10</offset>
        <radius>14</radius>
        <flighttype>gate</flighttype>
        <performance-class>jet_transport</performance-class>
        <registration>TC-AAE</registration>
        <heavy>false</heavy>
    </aircraft>
    <aircraft>
        <model>Aircraft/737/737-PegasusAirlines.xml</model>
        <livery>PGT</livery>
        <airline>PGT</airline>
        <home-port>LTFJ</home-port>
        <required-aircraft>737LTFJPGT</required-aircraft>
        <actype>737-82R</actype>
        <offset>10</offset>
        <radius>14</radius>
        <flighttype>gate</flighttype>
        <performance-class>jet_transport</performance-class>
        <registration>TC-AAH</registration>
        <heavy>false</heavy>
    </aircraft>
        <flight>
            <callsign>SunTurk0283</callsign>
            <required-aircraft>737PGT</required-aircraft>
            <fltrules>IFR</fltrules>
            <departure>
                <port>EHAM</port>
                <time>2/05:40:00</time>
            </departure>
            <cruise-alt>290</cruise-alt>
            <arrival>
                <port>LTAY</port>
                <time>2/08:45:00</time>
            </arrival>
            <repeat>WEEK</repeat>
        </flight>
        <flight>
            <callsign>SunTurk0283</callsign>
            <required-aircraft>737PGT</required-aircraft>
            <fltrules>IFR</fltrules>
            <departure>
                <port>EHAM</port>
                <time>6/05:40:00</time>
            </departure>
            <cruise-alt>290</cruise-alt>
            <arrival>
                <port>LTAY</port>
                <time>6/08:45:00</time>
            </arrival>
            <repeat>WEEK</repeat>
        </flight>
        <flight>
            <callsign>SunTurk0284</callsign>
            <required-aircraft>737PGT</required-aircraft>
            <fltrules>IFR</fltrules>
            <departure>
                <port>LTAY</port>
                <time>2/09:35:00</time>
            </departure>
            <cruise-alt>290</cruise-alt>
            <arrival>
                <port>EHAM</port>
                <time>2/14:15:00</time>
            </arrival>
            <repeat>WEEK</repeat>
        </flight>
        <flight>
            <callsign>SunTurk0284</callsign>
            <required-aircraft>737PGT</required-aircraft>
            <fltrules>IFR</fltrules>
            <departure>
                <port>LTAY</port>
                <time>6/09:35:00</time>
            </departure>
            <cruise-alt>290</cruise-alt>
            <arrival>
                <port>EHAM</port>
                <time>6/14:15:00</time>
            </arrival>
            <repeat>WEEK</repeat>
        </flight>
        <flight>
            <callsign>SunTurk0671</callsign>
            <required-aircraft>737LTFJPGT</required-aircraft>
            <fltrules>IFR</fltrules>
            <departure>
                <port>LTFJ</port>
                <time>2/07:50:00</time>
            </departure>
            <cruise-alt>290</cruise-alt>
            <arrival>
                <port>EHAM</port>
                <time>2/10:15:00</time>
            </arrival>
            <repeat>WEEK</repeat>
        </flight>
        <flight>
            <callsign>SunTurk0671</callsign>
            <required-aircraft>737LTFJPGT</required-aircraft>
            <fltrules>IFR</fltrules>
            <departure>
                <port>LTFJ</port>
                <time>6/07:50:00</time>
            </departure>
            <cruise-alt>290</cruise-alt>
            <arrival>
                <port>EHAM</port>
                <time>6/10:15:00</time>
            </arrival>
            <repeat>WEEK</repeat>
        </flight>
        <flight>
            <callsign>SunTurk0672</callsign>
            <required-aircraft>737LTFJPGT</required-aircraft>
            <fltrules>IFR</fltrules>
            <departure>
                <port>EHAM</port>
                <time>2/11:05:00</time>
            </departure>
            <cruise-alt>290</cruise-alt>
            <arrival>
                <port>LTFJ</port>
                <time>2/15:20:00</time>
            </arrival>
            <repeat>WEEK</repeat>
        </flight>
        <flight>
            <callsign>SunTurk0672</callsign>
            <required-aircraft>737LTFJPGT</required-aircraft>
            <fltrules>IFR</fltrules>
            <departure>
                <port>EHAM</port>
                <time>6/11:05:00</time>
            </departure>
            <cruise-alt>290</cruise-alt>
            <arrival>
                <port>LTFJ</port>
                <time>6/15:20:00</time>
            </arrival>
            <repeat>WEEK</repeat>
        </flight>
</trafficlist>
